{
  "doc_type": "lk_pmd_press_release",
  "doc_id": "2025-06-04-9fe07c",
  "num": "9fe07c",
  "date_str": "2025-06-04",
  "description": "Internal Affairs Unit Established at the Presidential Secretariat",
  "url_metadata": "https://pmd.gov.lk/news/internal-affairs-unit-established-at-the-presidential-secretariat/",
  "lang": "en",
  "article_title": "Internal Affairs Unit Established at the Presidential Secretariat",
  "article_body_paragraphs": [
    "An Internal Affairs Unit has been established within the Presidential Secretariat premises to receive inquiries and complaints related to the services provided by the Presidential Secretariat. The unit was officially declared open today (04) by the Secretary to the President, Dr. Nandika Sanath Kumanayake.",
    "Inquiries or complaints related to the services can be submitted to the following address:\nThe Internal Affairs Unit\nPresidential Secretariat, Colombo 01\nTelephone: 011 235 4495\nWhatsApp: 071 640 2654\nEmail: iau@presidentsoffice.lk"
  ]
}